muxy/__init__.py
muxy/py.typed
muxy/router.py
muxy/rsgi.py
muxy/tree.py
muxy-0.1.0.dev12.dist-info/licenses/LICENSE
muxy-0.1.0.dev12.dist-info/WHEEL
muxy-0.1.0.dev12.dist-info/METADATA
muxy-0.1.0.dev12.dist-info/RECORD
