Metadata-Version: 2.4
Name: muxy
Version: 0.1.0.dev12
Summary: Lightweight router for building HTTP services.
Keywords: http,router,rsgi
License-Expression: MIT
License-File: LICENSE
Classifier: Development Status :: 2 - Pre-Alpha
Classifier: Environment :: Web Environment
Classifier: Framework :: AsyncIO
Classifier: Intended Audience :: Developers
Classifier: License :: OSI Approved :: MIT License
Classifier: Operating System :: OS Independent
Classifier: Programming Language :: Python
Classifier: Programming Language :: Python :: 3
Classifier: Programming Language :: Python :: 3 :: Only
Classifier: Programming Language :: Python :: 3.14
Classifier: Programming Language :: Python :: Implementation :: CPython
Classifier: Topic :: Internet :: WWW/HTTP :: HTTP Servers
Classifier: Topic :: Software Development :: Libraries :: Python Modules
Classifier: Typing :: Typed
Requires-Python: >=3.14
Project-URL: Changelog, https://github.com/oliverlambson/muxy/blob/main/CHANGELOG.md
Project-URL: Issues, https://github.com/oliverlambson/muxy/issues
Project-URL: Repository, https://github.com/oliverlambson/muxy
